odoo/addons/web_widget_product_label_section_and_note_name_visibility/README.rst
odoo/addons/web_widget_product_label_section_and_note_name_visibility/__init__.py
odoo/addons/web_widget_product_label_section_and_note_name_visibility/__manifest__.py
odoo/addons/web_widget_product_label_section_and_note_name_visibility/i18n/it.po
odoo/addons/web_widget_product_label_section_and_note_name_visibility/i18n/web_widget_product_label_section_and_note.pot
odoo/addons/web_widget_product_label_section_and_note_name_visibility/i18n/web_widget_product_label_section_and_note_name_visibility.pot
odoo/addons/web_widget_product_label_section_and_note_name_visibility/readme/CONTRIBUTORS.md
odoo/addons/web_widget_product_label_section_and_note_name_visibility/readme/DESCRIPTION.md
odoo/addons/web_widget_product_label_section_and_note_name_visibility/readme/ROADMAP.md
odoo/addons/web_widget_product_label_section_and_note_name_visibility/readme/USAGE.md
odoo/addons/web_widget_product_label_section_and_note_name_visibility/static/description/icon.png
odoo/addons/web_widget_product_label_section_and_note_name_visibility/static/description/index.html
odoo/addons/web_widget_product_label_section_and_note_name_visibility/static/src/components/product_label_section_and_note_field/product_label_section_and_note_field.esm.js
odoo/addons/web_widget_product_label_section_and_note_name_visibility/static/src/components/product_label_section_and_note_field/product_label_section_and_note_field.xml
odoo_addon_web_widget_product_label_section_and_note_name_visibility-18.0.1.0.1.dist-info/METADATA
odoo_addon_web_widget_product_label_section_and_note_name_visibility-18.0.1.0.1.dist-info/WHEEL
odoo_addon_web_widget_product_label_section_and_note_name_visibility-18.0.1.0.1.dist-info/top_level.txt
odoo_addon_web_widget_product_label_section_and_note_name_visibility-18.0.1.0.1.dist-info/RECORD
