Metadata-Version: 2.1
Name: odoo-addon-web_widget_product_label_section_and_note_name_visibility
Version: 18.0.1.0.1
Requires-Python: >=3.10
Requires-Dist: odoo==18.0.*
Summary: Alternate the visibility of the product and description.
Home-page: https://github.com/OCA/web
License: AGPL-3
Author: Tecnativa, Odoo Community Association (OCA), Odoo S.A.
Author-email: support@odoo-community.org
Classifier: Programming Language :: Python
Classifier: Framework :: Odoo
Classifier: Framework :: Odoo :: 18.0
Classifier: License :: OSI Approved :: GNU Affero General Public License v3
